svcco/__init__.py
svcco/test_rotation.py
svcco/tree.py
svcco/branch_addition/__init__.py
svcco/branch_addition/add_bifurcation.py
svcco/branch_addition/add_branches.py
svcco/branch_addition/add_branches_v2.py
svcco/branch_addition/add_branches_v3.py
svcco/branch_addition/add_depths.py
svcco/branch_addition/add_edge.py
svcco/branch_addition/add_flow.py
svcco/branch_addition/add_geodesic_path.py
svcco/branch_addition/basis.py
svcco/branch_addition/calculate_length.py
svcco/branch_addition/calculate_radii.py
svcco/branch_addition/check.py
svcco/branch_addition/close.py
svcco/branch_addition/finite_difference.py
svcco/branch_addition/geodesic.py
svcco/branch_addition/get_path.py
svcco/branch_addition/get_point.py
svcco/branch_addition/local_func_v5.py
svcco/branch_addition/local_func_v6.py
svcco/branch_addition/local_func_v7.py
svcco/branch_addition/sample_triad.py
svcco/branch_addition/set_root.py
svcco/branch_addition/set_root_homogeneous_nonconvex.py
svcco/branch_addition/triangle.py
svcco/branch_addition/update.py
svcco/branch_addition/update_geodesic.py
svcco/collision/__init__.py
svcco/collision/collision.py
svcco/collision/obb.py
svcco/collision/obb_unit_tests.py
svcco/collision/sphere_proximity.py
svcco/collision/sphere_proximity_unit_tests.py
svcco/forest_utils/__init__.py
svcco/forest_utils/compete_add.py
svcco/forest_utils/connect.py
svcco/forest_utils/connect_collision.py
svcco/forest_utils/optimize_connection.py
svcco/forest_utils/optimize_connection_v2.py
svcco/forest_utils/optimize_connection_v3.py
svcco/forest_utils/optimize_connection_v4.py
svcco/forest_utils/optimize_connection_v5.py
svcco/forest_utils/smooth.py
svcco/implicit/__init__.py
svcco/implicit/derivative.py
svcco/implicit/implicit.py
svcco/implicit/load.py
svcco/implicit/sampling.py
svcco/implicit/weingarten_map.py
svcco/implicit/core/__init__.py
svcco/implicit/core/a_matrix.py
svcco/implicit/core/h_matrix.py
svcco/implicit/core/m_matrix.py
svcco/implicit/core/n_matrix.py
svcco-0.6.31.dist-info/LICENSE.txt
svcco-0.6.31.dist-info/METADATA
svcco-0.6.31.dist-info/WHEEL
svcco-0.6.31.dist-info/top_level.txt
svcco-0.6.31.dist-info/RECORD
