Metadata-Version: 2.1
Name: svcco
Version: 0.6.31
Summary: Automated Vascular Generation and CFD Simulation
Home-page: https://zasexton.github.io/svcco/
Author: Zachary Sexton
Author-email: zsexton@stanford.edu
License: MIT
Classifier: Intended Audience :: Science/Research
Classifier: License :: OSI Approved :: MIT License
Classifier: Programming Language :: Python
Classifier: Programming Language :: Python :: 3.7
Classifier: Programming Language :: Python :: 3.8
Classifier: Programming Language :: Python :: 3.9
Classifier: Topic :: Scientific/Engineering
Classifier: Operating System :: Microsoft :: Windows
Classifier: Operating System :: POSIX :: Linux
Classifier: Operating System :: POSIX
Classifier: Operating System :: Unix
Classifier: Operating System :: MacOS
Requires-Python: >=3.7
License-File: LICENSE.txt
Requires-Dist: pyvista (==0.34.2)
Requires-Dist: numpy (==1.21.0)
Requires-Dist: setuptools (>=62.3.3)
Requires-Dist: tqdm (>=4.63.0)
Requires-Dist: matplotlib (>=3.3.4)
Requires-Dist: vtk (>=9.0.0)
Requires-Dist: binarytree (>=6.5.1)
Requires-Dist: memory-profiler (>=0.60.0)
Requires-Dist: networkx (>=2.5.1)
Requires-Dist: pydotplus (>=2.0.2)
Requires-Dist: numba (>=0.55.1)
Requires-Dist: seaborn (>=0.11.2)
Requires-Dist: tetgen (>=0.6.0)
Requires-Dist: scipy (>=1.6.0)
Requires-Dist: pymeshfix (>=0.15.0)
Requires-Dist: geomdl (>=5.3.1)
Requires-Dist: sympy (>=1.9)
Requires-Dist: plotly (>=5.1.0)
Requires-Dist: scikit-image (>=0.16.1)
Requires-Dist: meshio (==5.3.4)
Requires-Dist: importlib-metadata
